<?xml version="1.0" encoding="UTF-8" standalone="yes"?>
<root>
<name>== (equality)</name>

<category>Control</category>

<subcategory>Relational Operators</subcategory>

<usage>Web &amp; Application</usage>

<example>
<code><![CDATA[
a = 23
b = 23
if a == b:
    println("variables a and b are equal")
]]></code>
</example>

<description><![CDATA[
Determines if two values are equivalent. The equality operator is different from the assignment operator.<br /> 
]]></description>

<syntax>
<c>value1</c> == <c>value2</c>
</syntax>

<parameter>
<label>value1</label>
<description><![CDATA[int, float, byte, boolean]]></description>
</parameter>

<parameter>
<label>value2</label>
<description><![CDATA[int, float, byte, boolean]]></description>
</parameter>

<returns></returns>

<related>greaterthan</related>
<related>lessthan</related>
<related>greaterthanorequalto</related>
<related>lessthanorequalto</related>
<related>inequality</related>

<availability>1.0</availability>

<type>Operator</type>

<partof>PYDE</partof>

</root>
